{
    "apiVersion": "1.0.0",
    "apis": [
        {
            "operations": [
                {
                    "authorizations": {},
                    "items": {
                        "$ref": "Namespace"
                    },
                    "method": "GET",
                    "nickname": "list_namespaces",
                    "parameters": [],
                    "responseMessages": [
                        {
                            "code": 500,
                            "message": "Server side error"
                        }
                    ],
                    "summary": "List all the namespaces",
                    "type": "array"
                }
            ],
            "path": "/v1/namespaces"
        },
        {
            "operations": [
                {
                    "authorizations": {},
                    "items": {
                        "$ref": "Source"
                    },
                    "method": "GET",
                    "nickname": "list_sources_by_namespace",
                    "parameters": [
                        {
                            "allowMultiple": false,
                            "name": "namespace",
                            "paramType": "path",
                            "required": true,
                            "type": "string"
                        }
                    ],
                    "responseMessages": [
                        {
                            "code": 400,
                            "message": "Invalid request"
                        },
                        {
                            "code": 404,
                            "message": "Namespace is not found"
                        },
                        {
                            "code": 500,
                            "message": "Server side error"
                        }
                    ],
                    "summary": "List all the sources of specified namespace",
                    "type": "array"
                }
            ],
            "path": "/v1/namespaces/{namespace}/sources"
        },
        {
            "operations": [
                {
                    "authorizations": {},
                    "items": {
                        "$ref": "Refresh"
                    },
                    "method": "GET",
                    "nickname": "list_refreshes_by_namespace",
                    "parameters": [
                        {
                            "allowMultiple": false,
                            "name": "namespace",
                            "paramType": "path",
                            "required": true,
                            "type": "string"
                        }
                    ],
                    "responseMessages": [
                        {
                            "code": 400,
                            "message": "Invalid request"
                        },
                        {
                            "code": 404,
                            "message": "Namespace is not found"
                        },
                        {
                            "code": 500,
                            "message": "Server side error"
                        }
                    ],
                    "summary": "List all refreshes of specified namespace",
                    "type": "array"
                }
            ],
            "path": "/v1/namespaces/{namespace}/refreshes"
        },
        {
            "operations": [
                {
                    "authorizations": {},
                    "method": "POST",
                    "nickname": "register_namespace_meta_attribute_mapping",
                    "notes": "The namespace name and the schema_id of Meta attribute schema should exist.",
                    "parameters": [
                        {
                            "allowMultiple": false,
                            "description": "Namespace for which meta attribute mappings will be registered",
                            "name": "namespace",
                            "paramType": "path",
                            "required": true,
                            "type": "string"
                        },
                        {
                            "name": "body",
                            "paramType": "body",
                            "required": true,
                            "type": "RegisterMetaAttributeRequest"
                        }
                    ],
                    "responseMessages": [
                        {
                            "code": 404,
                            "message": "Entity not found"
                        },
                        {
                            "code": 400,
                            "message": "Invalid request"
                        },
                        {
                            "code": 500,
                            "message": "Server side error"
                        }
                    ],
                    "summary": "Register the specified meta attribute schema_id to the specified namespace name.",
                    "type": "MetaAttributeNamespaceMapping"
                },
                {
                    "authorizations": {},
                    "method": "DELETE",
                    "nickname": "delete_namespace_meta_attribute_mapping",
                    "notes": "The namespace name and the schema_id of Meta attribute schema should exist.",
                    "parameters": [
                        {
                            "allowMultiple": false,
                            "description": "Namespace for which meta attribute mappings will be deleted",
                            "name": "namespace",
                            "paramType": "path",
                            "required": true,
                            "type": "string"
                        },
                        {
                            "name": "body",
                            "paramType": "body",
                            "required": true,
                            "type": "RegisterMetaAttributeRequest"
                        }
                    ],
                    "responseMessages": [
                        {
                            "code": 404,
                            "message": "Entity not found"
                        },
                        {
                            "code": 400,
                            "message": "Invalid request"
                        },
                        {
                            "code": 500,
                            "message": "Server side error"
                        }
                    ],
                    "summary": "Remove the specified meta attribute schema_id mapping from the specified namespace name.",
                    "type": "MetaAttributeNamespaceMapping"
                },
                {
                    "authorizations": {},
                    "items": {
                        "$ref": "MetaAttributeNamespaceMapping"
                    },
                    "method": "GET",
                    "nickname": "get_namespace_meta_attribute_mappings",
                    "notes": "The namespace name should exist.",
                    "parameters": [
                        {
                            "allowMultiple": false,
                            "description": "Namespace for which meta attributes will be fetched",
                            "name": "namespace",
                            "paramType": "path",
                            "required": true,
                            "type": "string"
                        }
                    ],
                    "responseMessages": [
                        {
                            "code": 400,
                            "message": "Invalid Namespace name supplied"
                        },
                        {
                            "code": 404,
                            "message": "Namespace not found"
                        },
                        {
                            "code": 500,
                            "message": "Server side error"
                        }
                    ],
                    "summary": "Get a list of all meta attribute schema_ids mapped to specified namespace name.",
                    "type": "array"
                }
            ],
            "path": "/v1/namespaces/{namespace}/meta_attr_mappings"
        }
    ],
    "basePath": "http://169.254.255.254:20912",
    "consumes": [
        "application/json"
    ],
    "models": {
        "MetaAttributeNamespaceMapping": {
            "id": "MetaAttributeNamespaceMapping",
            "properties": {
                "meta_attribute_schema_id": {
                    "description": "Avro Schema ID of meta attribute.",
                    "type": "integer"
                },
                "namespace_id": {
                    "description": "ID to distinguish a unique namespace.",
                    "type": "integer"
                }
            },
            "required": [
                "meta_attribute_schema_id",
                "namespace_id"
            ]
        },
        "Namespace": {
            "id": "Namespace",
            "properties": {
                "created_at": {
                    "description": "When this namespace is created",
                    "format": "date-time",
                    "type": "string"
                },
                "name": {
                    "description": "Namespace, such as yelpmain.db, etc",
                    "type": "string"
                },
                "namespace_id": {
                    "description": "Namespace ID",
                    "type": "integer"
                },
                "updated_at": {
                    "description": "When this namespace is last updated",
                    "format": "date-time",
                    "type": "string"
                }
            }
        },
        "Refresh": {
            "id": "Refresh",
            "properties": {
                "avg_rows_per_second_cap": {
                    "description": "This field throttles the per-instance throughput of the refresh runner once the refresh is actually run. We will sleep in between batch row gets to limit it to this cap (default: null)",
                    "type": "integer"
                },
                "batch_size": {
                    "description": "Number of rows to refresh per batch.",
                    "type": "integer"
                },
                "created_at": {
                    "description": "When this refresh is created.",
                    "format": "date-time",
                    "type": "string"
                },
                "filter_condition": {
                    "description": "This field contains the expression used to filter the records that must be refreshed. E.g. It may be a MySQL where clause if the source of the refresh is a MySQL table.",
                    "type": "string"
                },
                "namespace_name": {
                    "description": "Name of the namespace the refresh is running on.",
                    "type": "string"
                },
                "offset": {
                    "description": "Represents the last known position that has been refreshed.",
                    "type": "integer"
                },
                "priority": {
                    "description": "Priority of this refresh. LOW=20, MAX=100",
                    "type": "integer"
                },
                "refresh_id": {
                    "description": "Refresh ID",
                    "type": "integer"
                },
                "source_name": {
                    "description": "Name of the source the refresh is running on.",
                    "type": "string"
                },
                "status": {
                    "description": "Current status of refresh.",
                    "enum": [
                        "NOT_STARTED",
                        "IN_PROGRESS",
                        "PAUSED",
                        "SUCCESS",
                        "FAILED"
                    ],
                    "type": "string"
                },
                "updated_at": {
                    "description": "When this refresh is last updated.",
                    "format": "date-time",
                    "type": "string"
                }
            }
        },
        "RegisterMetaAttributeRequest": {
            "id": "RegisterMetaAttributeRequest",
            "properties": {
                "meta_attribute_schema_id": {
                    "description": "AvroSchema ID of Meta Attribute schema to be mapped.",
                    "type": "integer"
                }
            },
            "required": [
                "meta_attribute_schema_id"
            ]
        },
        "Source": {
            "id": "Source",
            "properties": {
                "category": {
                    "description": "Category that this source belongs to",
                    "type": "string"
                },
                "created_at": {
                    "description": "When this source is created",
                    "format": "date-time",
                    "type": "string"
                },
                "name": {
                    "description": "Name of the source, such as 'User' for table User.",
                    "type": "string"
                },
                "namespace": {
                    "$ref": "Namespace",
                    "description": "Namespace of the source"
                },
                "owner_email": {
                    "description": "Email address of the source owner",
                    "type": "string"
                },
                "source_id": {
                    "description": "Source ID",
                    "type": "integer"
                },
                "updated_at": {
                    "description": "When this source is last updated",
                    "format": "date-time",
                    "type": "string"
                }
            }
        }
    },
    "produces": [
        "application/json"
    ],
    "resourcePath": "/v1/namespaces",
    "swaggerVersion": "1.2"
}
