<?xml version="1.0" encoding="UTF-8"?>
<databaseChangeLog xmlns="http://www.liquibase.org/xml/ns/dbchangelog" xmlns:xsi="http://www.w3.org/2001/XMLSchema-instance" xsi:schemaLocation="http://www.liquibase.org/xml/ns/dbchangelog http://www.liquibase.org/xml/ns/dbchangelog/dbchangelog-3.1.xsd">
    <changeSet author="psuben" id="1445967185">
        <comment>Adding Refresh Info table - DATAPIPE-560</comment>
        <createTable tableName="refresh_info">
            <column autoIncrement="true" name="id" type="INT(11)">
                <constraints primaryKey="true"/>
            </column>
            <column name="table_identifier" type="VARCHAR(255)">
                <constraints nullable="false"/>
            </column>
            <column name="refresh_status" type="INT(11)">
                <constraints nullable="false"/>
            </column>
            <column name="last_refreshed_at" type="INT(11)">
                <constraints nullable="false"/>
            </column>
        </createTable>
        <modifySql dbms="mysql">
            <append value=" ENGINE=InnoDB DEFAULT CHARSET=utf8 COLLATE=utf8_unicode_ci"/>
        </modifySql>
    </changeSet>

    <changeSet author="psuben" id="">
        <comment>Add unique constraint to refresh_info table</comment>
        <addUniqueConstraint columnNames="table_identifier"
                             constraintName="table_id_unique_constraint"
                             tableName="refresh_info"/>
    </changeSet>
</databaseChangeLog>